{
"name": "Sector 3",
"abbrev_name": "3",
"ref_id": "sector_3",
"author": "Ghast",
"data_stride": 2,
"data":[
    ". . . e0. . . . ",
    ". . . | . . . . ",
    ". 2 ~ 1 ~ 4 . . ",
    ". 3 . . . * . . ",
    ". * * . * * . . ",
    ". . 7 6 5 . . . ",
    ". . | . . . . . ",
    ". . 8 ~ 9 . . . ",
    ". . . . e1. . . "
],
"lvl_1": "help",
"lvl_2": "boost",
"lvl_3": "pit_of_despair",
"lvl_4": "teleporter",
"lvl_5": "duality",
"lvl_6": "split",
"lvl_7": "control",
"lvl_8": "release",
"lvl_9": "pathways",
"bg_triangles": {
    "top": [],
    "left": [],
    "bottom": [],
    "right": [],
    "top_left": [],
    "bottom_left": [
        [[28, 0], [45, -88], [58, 0], "dark_gray"],
        [[0, -192], [45, -88], [45, 0], "light_gray"],
        [[0, -192], [0, 0], [45, 0], "light_gray"]
    ],
    "top_right": [
        [[-55, 84], [0, 104], [0, 60], "dark_gray"],
        [[-55, 84], [0, 60], [0, 0], "light_gray"],
        [[-77, 32], [-19, 35], [-27, 47], "dark_gray"],
        [[-77, 32], [-13, 41], [0, 0], "light_gray"],
        [[-77, 32], [-91, 0], [0, 0], "light_gray"]
    ],
    "bottom_right": [
        [[-32, 0], [0, -40], [0, 0], "dark_gray"],
        [[-72, 0], [0, -50], [-32, 0], "light_gray"],
        [[0, -50], [-32, 0], [0, 0], "light_gray"]
    ],
    "center":[]
}
}
